[{"tax": [{"cutoff": "5000", "taxrate": "1"}, {"cutoff": "10000", "taxrate": "2"}, {"cutoff": "15000", "taxrate": "3"}, {"cutoff": "20000", "taxrate": "4"}, {"cutoff": "25000", "taxrate": "5"}, {"cutoff": "30000", "taxrate": "6"}, {"cutoff": "Inf", "taxrate": "7"}], "year": "1966"}, {"tax": [{"cutoff": "4000", "taxrate": "1"}, {"cutoff": "7000", "taxrate": "2"}, {"cutoff": "10000", "taxrate": "3"}, {"cutoff": "13000", "taxrate": "4"}, {"cutoff": "16000", "taxrate": "5"}, {"cutoff": "19000", "taxrate": "6"}, {"cutoff": "22000", "taxrate": "7"}, {"cutoff": "25000", "taxrate": "8"}, {"cutoff": "28000", "taxrate": "9"}, {"cutoff": "Inf", "taxrate": "10"}], "year": "1972"}, {"tax": [{"cutoff": "4000", "taxrate": "1"}, {"cutoff": "7000", "taxrate": "2"}, {"cutoff": "10000", "taxrate": "3"}, {"cutoff": "13000", "taxrate": "4"}, {"cutoff": "16000", "taxrate": "5"}, {"cutoff": "19000", "taxrate": "6"}, {"cutoff": "22000", "taxrate": "7"}, {"cutoff": "25000", "taxrate": "8"}, {"cutoff": "28000", "taxrate": "9"}, {"cutoff": "31000", "taxrate": "10"}, {"cutoff": "Inf", "taxrate": "11"}], "year": "1985"}, {"tax": [{"cutoff": "3420", "taxrate": "0"}, {"cutoff": "10420", "taxrate": "1"}, {"cutoff": "15620", "taxrate": "2"}, {"cutoff": "20840", "taxrate": "3"}, {"cutoff": "26160", "taxrate": "4"}, {"cutoff": "31420", "taxrate": "5"}, {"cutoff": "36660", "taxrate": "6"}, {"cutoff": "41860", "taxrate": "7"}, {"cutoff": "47120", "taxrate": "8"}, {"cutoff": "52360", "taxrate": "9"}, {"cutoff": "57580", "taxrate": "10"}, {"cutoff": "Inf", "taxrate": "11"}], "year": "1986"}, {"tax": [{"cutoff": "7300", "taxrate": "1"}, {"cutoff": "17300", "taxrate": "2"}, {"cutoff": "27300", "taxrate": "4"}, {"cutoff": "37900", "taxrate": "6"}, {"cutoff": "47900", "taxrate": "8"}, {"cutoff": "Inf", "taxrate": "9.3"}], "year": "1990"}, {"tax": [{"cutoff": "8788", "taxrate": "1"}, {"cutoff": "20828", "taxrate": "2"}, {"cutoff": "32870", "taxrate": "4"}, {"cutoff": "45632", "taxrate": "6"}, {"cutoff": "57670", "taxrate": "8"}, {"cutoff": "200000", "taxrate": "9.3"}, {"cutoff": "400000", "taxrate": "10"}, {"cutoff": "Inf", "taxrate": "11"}], "year": "1992"}, {"tax": [{"cutoff": "9662", "taxrate": "1"}, {"cutoff": "22898", "taxrate": "2"}, {"cutoff": "36136", "taxrate": "4"}, {"cutoff": "50166", "taxrate": "6"}, {"cutoff": "63400", "taxrate": "8"}, {"cutoff": "219872", "taxrate": "9.3"}, {"cutoff": "439744", "taxrate": "10"}, {"cutoff": "Inf", "taxrate": "11"}], "year": "1995"}, {"tax": [{"cutoff": "10262", "taxrate": "1"}, {"cutoff": "24322", "taxrate": "2"}, {"cutoff": "38386", "taxrate": "4"}, {"cutoff": "53288", "taxrate": "6"}, {"cutoff": "67346", "taxrate": "8"}, {"cutoff": "67347", "taxrate": "9.3"}], "year": "2000"}, {"tax": [{"cutoff": "12294", "taxrate": "1"}, {"cutoff": "29142", "taxrate": "2"}, {"cutoff": "45994", "taxrate": "4"}, {"cutoff": "63850", "taxrate": "6"}, {"cutoff": "80692", "taxrate": "8"}, {"cutoff": "80693", "taxrate": "9.3"}], "year": "2004"}, {"tax": [{"cutoff": "13244", "taxrate": "1"}, {"cutoff": "31396", "taxrate": "2"}, {"cutoff": "49552", "taxrate": "4"}, {"cutoff": "68788", "taxrate": "6"}, {"cutoff": "86934", "taxrate": "8"}, {"cutoff": "1000000", "taxrate": "9.3"}, {"cutoff": "Inf", "taxrate": "10.3"}], "year": "2007"}, {"tax": [{"cutoff": "14336", "taxrate": "1"}, {"cutoff": "33988", "taxrate": "2"}, {"cutoff": "53642", "taxrate": "4"}, {"cutoff": "74466", "taxrate": "6"}, {"cutoff": "94110", "taxrate": "8"}, {"cutoff": "1000000", "taxrate": "9.3"}, {"cutoff": "Inf", "taxrate": "10.3"}], "year": "2008"}, {"tax": [{"cutoff": "14248", "taxrate": "1.25"}, {"cutoff": "33780", "taxrate": "2.25"}, {"cutoff": "53314", "taxrate": "4.25"}, {"cutoff": "74010", "taxrate": "6.25"}, {"cutoff": "93532", "taxrate": "8.25"}, {"cutoff": "1000000", "taxrate": "9.55"}, {"cutoff": "Inf", "taxrate": "10.55"}], "year": "2010"}, {"tax": [{"cutoff": "14632", "taxrate": "1"}, {"cutoff": "34692", "taxrate": "2"}, {"cutoff": "54754", "taxrate": "4"}, {"cutoff": "76008", "taxrate": "6"}, {"cutoff": "96058", "taxrate": "8"}, {"cutoff": "1000000", "taxrate": "9.3"}, {"cutoff": "Inf", "taxrate": "10.3"}], "year": "2011"}, {"tax": [{"cutoff": "14910", "taxrate": "1"}, {"cutoff": "35352", "taxrate": "2"}, {"cutoff": "55794", "taxrate": "4"}, {"cutoff": "77452", "taxrate": "6"}, {"cutoff": "97884", "taxrate": "8"}, {"cutoff": "500000", "taxrate": "9.3"}, {"cutoff": "600000", "taxrate": "10.3"}, {"cutoff": "1000000", "taxrate": "11.3"}, {"cutoff": "Inf", "taxrate": "13.3"}], "year": "2012"}, {"tax": [{"cutoff": "15498", "taxrate": "1"}, {"cutoff": "36742", "taxrate": "2"}, {"cutoff": "57990", "taxrate": "4"}, {"cutoff": "80500", "taxrate": "6"}, {"cutoff": "101738", "taxrate": "8"}, {"cutoff": "519688", "taxrate": "9.3"}, {"cutoff": "623624", "taxrate": "10.3"}, {"cutoff": "1000000", "taxrate": "11.3"}, {"cutoff": "1039374", "taxrate": "12.3"}, {"cutoff": "Inf", "taxrate": "13.3"}], "year": "2014"}]